{
  "performance_optimizations": {
    "next_config_updates": {
      "status": "\u2705 Implemented",
      "changes": [
        "Enabled image optimization with AVIF/WebP formats",
        "Configured 30-day image caching TTL",
        "Enabled experimental optimizations (CSS, images, workers)",
        "Configured React compiler optimizations",
        "Enabled SWC minification and compression",
        "Added comprehensive caching headers",
        "Enabled PWA support for offline capabilities",
        "Configured font optimization and loading strategies"
      ],
      "expected_impact": {
        "image_loading": "30-50% faster",
        "bundle_size": "10-20% reduction",
        "rendering": "15-25% improvement",
        "caching": "90% cache hit rate for static assets"
      }
    },
    "code_splitting": {
      "status": "\u2705 Already Implemented (MainApp)",
      "changes": [
        "React.lazy() for panel components (Chat, Agents, Memory, Settings, Projects, Marketplace)",
        "Suspense boundaries with loading skeletons",
        "Dynamic imports for lazy-loaded components",
        "Optimized bundle splitting strategy"
      ],
      "expected_impact": {
        "initial_load": "40-60% reduction in JavaScript",
        "time_to_interactive": "30-50% improvement",
        "bundle_size": "Separate chunks for each panel"
      }
    }
  },
  "implementation_priority": [
    {
      "category": "JavaScript Execution Optimization",
      "priority": "CRITICAL",
      "current_metric": "TBT: 2,774ms",
      "target": "<300ms",
      "impact": "90% reduction in main thread blocking"
    },
    {
      "category": "API Response Optimization",
      "priority": "CRITICAL",
      "current_metric": "8,808ms",
      "target": "<500ms",
      "impact": "95% improvement in server response times"
    }
  ]
}